circle/__init__.py
circle/nid.py
circle/robicircle.py
circle/test.py
circlerobi-1.1.1.dist-info/LICENSE
circlerobi-1.1.1.dist-info/METADATA
circlerobi-1.1.1.dist-info/WHEEL
circlerobi-1.1.1.dist-info/top_level.txt
circlerobi-1.1.1.dist-info/RECORD
