Metadata-Version: 2.1
Name: circlerobi
Version: 1.1.1
Summary: Robi and Airtel CIRCLE project.
Home-page: https://github.com/Aru-Ofc-git/CIRCLE_TOOLS.git
Author: Ariful Islam Arman
Author-email: aru.ofc@yahoo.com
Project-URL: Bug Tracker, https://github.com/pypa/sampleproject/issues
Classifier: Development Status :: 5 - Production/Stable
Classifier: Programming Language :: Python :: 3
Classifier: Programming Language :: Python :: 3.5
Classifier: Programming Language :: Python
Classifier: License :: OSI Approved :: MIT License
Classifier: Operating System :: OS Independent
Requires-Python: >=3.6
License-File: LICENSE
